{"updatedDate":"2023-08-15","data":{"code":"MM","name":"Myanmar (Burma)","description":"Myanmar’s aim is to harness its potential to help create a better governed, more peaceful and prosperous Myanmar that uses its increased wealth to improve education and health services, and reduce poverty. The remarkable process of change has given the UK a great opportunity to transform the lives of vulnerable people in Myanmar.   \n\n## Top priorities \n* promoting good governance, including improved transparency and the rule of law  \n* promoting inclusive growth and responsible investment  \n* strengthening parliament and elected bodies at sub-national levels \n*  helping the process of peace building and ethnic reconciliation \n* supporting productive and sustainable livelihoods and improved access to better health and education services  \n\n## Further resources \n[Myanmar Operational Plan](https://www.gov.uk/government/publications/dfid-burma-operational-plan-2014)  \n[Myanmar page on GOV.UK website](https://www.gov.uk/government/world/myanmar)","population":53897154,"population_year":2015,"lifeExpectancy":65.85785366,"incomeLevel":"Lower middle income","belowPovertyLine":"","belowPovertyLine_year":"","fertilityRate":2.204,"fertilityRate_year":2014,"gdpGrowthRate":7.294031845,"gdpGrowthRate_year":2015,"countryBudget":69540380.89285713,"countryBudgetCurrency":"GBP"}}
