{"updatedDate":"2023-07-24","data":{"map_data":["{\"PH\":{\"country\":\"Philippines (the)\", \"id\":\"PH\", \"projects\":35, \"budget\":845368.35, \"flag\":\"/images/flags/ph.png\"}, \"IN\":{\"country\":\"India\", \"id\":\"IN\", \"projects\":51, \"budget\":28578966.75, \"flag\":\"/images/flags/in.png\"}, \"GH\":{\"country\":\"Ghana\", \"id\":\"GH\", \"projects\":39, \"budget\":17676308.6, \"flag\":\"/images/flags/gh.png\"}, \"RW\":{\"country\":\"Rwanda\", \"id\":\"RW\", \"projects\":23, \"budget\":31340724.38, \"flag\":\"/images/flags/rw.png\"}, \"KE\":{\"country\":\"Kenya\", \"id\":\"KE\", \"projects\":53, \"budget\":83292537.39, \"flag\":\"/images/flags/ke.png\"}, \"NA\":{\"country\":\"Namibia\", \"id\":\"NA\", \"projects\":18, \"budget\":2676.67, \"flag\":\"/images/flags/na.png\"}, \"SY\":{\"country\":\"Syrian Arab Republic (the)\", \"id\":\"SY\", \"projects\":25, \"budget\":87397616.71, \"flag\":\"/images/flags/sy.png\"}, \"VN\":{\"country\":\"Viet Nam\", \"id\":\"VN\", \"projects\":37, \"budget\":1923977.83, \"flag\":\"/images/flags/vn.png\"}, \"AL\":{\"country\":\"Albania\", \"id\":\"AL\", \"projects\":14, \"budget\":2676.67, \"flag\":\"/images/flags/al.png\"}, \"EC\":{\"country\":\"Ecuador\", \"id\":\"EC\", \"projects\":17, \"budget\":2676.67, \"flag\":\"/images/flags/ec.png\"}, \"CR\":{\"country\":\"Costa Rica\", \"id\":\"CR\", \"projects\":12, \"budget\":2676.67, \"flag\":\"/images/flags/cr.png\"}, \"NI\":{\"country\":\"Nicaragua\", \"id\":\"NI\", \"projects\":15, \"budget\":25397.03, \"flag\":\"/images/flags/ni.png\"}, \"SV\":{\"country\":\"El Salvador\", \"id\":\"SV\", \"projects\":14, \"budget\":2676.67, \"flag\":\"/images/flags/sv.png\"}, \"CO\":{\"country\":\"Colombia\", \"id\":\"CO\", \"projects\":32, \"budget\":14725580.03, \"flag\":\"/images/flags/co.png\"}, \"PA\":{\"country\":\"Panama\", \"id\":\"PA\", \"projects\":12, \"budget\":2676.67, \"flag\":\"/images/flags/pa.png\"}, \"HN\":{\"country\":\"Honduras\", \"id\":\"HN\", \"projects\":14, \"budget\":2676.67, \"flag\":\"/images/flags/hn.png\"}, \"MX\":{\"country\":\"Mexico\", \"id\":\"MX\", \"projects\":32, \"budget\":2676.67, \"flag\":\"/images/flags/mx.png\"}, \"PE\":{\"country\":\"Peru\", \"id\":\"PE\", \"projects\":26, \"budget\":2676.67, \"flag\":\"/images/flags/pe.png\"}, \"GT\":{\"country\":\"Guatemala\", \"id\":\"GT\", \"projects\":14, \"budget\":2676.67, \"flag\":\"/images/flags/gt.png\"}, \"ID\":{\"country\":\"Indonesia\", \"id\":\"ID\", \"projects\":50, \"budget\":8449464.02, \"flag\":\"/images/flags/id.png\"}, \"ET\":{\"country\":\"Ethiopia\", \"id\":\"ET\", \"projects\":42, \"budget\":97671333.25, \"flag\":\"/images/flags/et.png\"}, \"ZM\":{\"country\":\"Zambia\", \"id\":\"ZM\", \"projects\":33, \"budget\":22081302.38, \"flag\":\"/images/flags/zm.png\"}, \"MW\":{\"country\":\"Malawi\", \"id\":\"MW\", \"projects\":36, \"budget\":24499704.77, \"flag\":\"/images/flags/mw.png\"}, \"BZ\":{\"country\":\"Belize\", \"id\":\"BZ\", \"projects\":12, \"budget\":2676.67, \"flag\":\"/images/flags/bz.png\"}, \"CN\":{\"country\":\"China\", \"id\":\"CN\", \"projects\":39, \"budget\":102176.67, \"flag\":\"/images/flags/cn.png\"}, \"CM\":{\"country\":\"Cameroon\", \"id\":\"CM\", \"projects\":25, \"budget\":2676.67, \"flag\":\"/images/flags/cm.png\"}, \"BW\":{\"country\":\"Botswana\", \"id\":\"BW\", \"projects\":15, \"budget\":2676.67, \"flag\":\"/images/flags/bw.png\"}, \"MZ\":{\"country\":\"Mozambique\", \"id\":\"MZ\", \"projects\":35, \"budget\":56784115.58, \"flag\":\"/images/flags/mz.png\"}, \"UG\":{\"country\":\"Uganda\", \"id\":\"UG\", \"projects\":42, \"budget\":25718500.14, \"flag\":\"/images/flags/ug.png\"}, \"KG\":{\"country\":\"Kyrgyzstan\", \"id\":\"KG\", \"projects\":13, \"budget\":7787740.67, \"flag\":\"/images/flags/kg.png\"}, \"LA\":{\"country\":\"Lao People's Democratic Republic (the)\", \"id\":\"LA\", \"projects\":18, \"budget\":2676.67, \"flag\":\"/images/flags/la.png\"}, \"MG\":{\"country\":\"Madagascar\", \"id\":\"MG\", \"projects\":22, \"budget\":2222708.56, \"flag\":\"/images/flags/mg.png\"}, \"MN\":{\"country\":\"Mongolia\", \"id\":\"MN\", \"projects\":13, \"budget\":2676.67, \"flag\":\"/images/flags/mn.png\"}, \"ML\":{\"country\":\"Mali\", \"id\":\"ML\", \"projects\":17, \"budget\":2602668.67, \"flag\":\"/images/flags/ml.png\"}, \"BR\":{\"country\":\"Brazil\", \"id\":\"BR\", \"projects\":43, \"budget\":13124547.99, \"flag\":\"/images/flags/br.png\"}, \"LK\":{\"country\":\"Sri Lanka\", \"id\":\"LK\", \"projects\":21, \"budget\":28892.47, \"flag\":\"/images/flags/lk.png\"}, \"MS\":{\"country\":\"Montserrat\", \"id\":\"MS\", \"projects\":20, \"budget\":78459810.67, \"flag\":\"/images/flags/ms.png\"}, \"PN\":{\"country\":\"Pitcairn\", \"id\":\"PN\", \"projects\":3, \"budget\":0.0, \"flag\":\"/images/flags/pn.png\"}, \"SH\":{\"country\":\"Saint Helena, Ascension and Tristan da Cunha\", \"id\":\"SH\", \"projects\":19, \"budget\":6010529.67, \"flag\":\"/images/flags/sh.png\"}, \"AO\":{\"country\":\"Angola\", \"id\":\"AO\", \"projects\":14, \"budget\":2676.67, \"flag\":\"/images/flags/ao.png\"}, \"ZW\":{\"country\":\"Zimbabwe\", \"id\":\"ZW\", \"projects\":33, \"budget\":20593388.23, \"flag\":\"/images/flags/zw.png\"}, \"BD\":{\"country\":\"Bangladesh\", \"id\":\"BD\", \"projects\":37, \"budget\":55209097.91, \"flag\":\"/images/flags/bd.png\"}, \"AM\":{\"country\":\"Armenia\", \"id\":\"AM\", \"projects\":16, \"budget\":4371280.03, \"flag\":\"/images/flags/am.png\"}, \"GE\":{\"country\":\"Georgia\", \"id\":\"GE\", \"projects\":17, \"budget\":4371280.03, \"flag\":\"/images/flags/ge.png\"}, \"BO\":{\"country\":\"Bolivia (Plurinational State of)\", \"id\":\"BO\", \"projects\":15, \"budget\":2676.67, \"flag\":\"/images/flags/bo.png\"}, \"KH\":{\"country\":\"Cambodia\", \"id\":\"KH\", \"projects\":20, \"budget\":299648.85, \"flag\":\"/images/flags/kh.png\"}, \"TH\":{\"country\":\"Thailand\", \"id\":\"TH\", \"projects\":32, \"budget\":256829.71, \"flag\":\"/images/flags/th.png\"}, \"LR\":{\"country\":\"Liberia\", \"id\":\"LR\", \"projects\":20, \"budget\":946693.56, \"flag\":\"/images/flags/lr.png\"}, \"FM\":{\"country\":\"Micronesia (Federated States of)\", \"id\":\"FM\", \"projects\":12, \"budget\":2676.67, \"flag\":\"/images/flags/fm.png\"}, \"NP\":{\"country\":\"Nepal\", \"id\":\"NP\", \"projects\":40, \"budget\":56459776.71, \"flag\":\"/images/flags/np.png\"}, \"NE\":{\"country\":\"Niger (the)\", \"id\":\"NE\", \"projects\":17, \"budget\":76938.67, \"flag\":\"/images/flags/ne.png\"}, \"PS\":{\"country\":\"Palestine, State of\", \"id\":\"PS\", \"projects\":19, \"budget\":6428046.67, \"flag\":\"/images/flags/ps.png\"}, \"SO\":{\"country\":\"Somalia\", \"id\":\"SO\", \"projects\":28, \"budget\":129598264.75, \"flag\":\"/images/flags/so.png\"}, \"SS\":{\"country\":\"South Sudan\", \"id\":\"SS\", \"projects\":26, \"budget\":51860842.91, \"flag\":\"/images/flags/ss.png\"}, \"TZ\":{\"country\":\"Tanzania, the United Republic of\", \"id\":\"TZ\", \"projects\":41, \"budget\":27829129.09, \"flag\":\"/images/flags/tz.png\"}, \"SZ\":{\"country\":\"Eswatini\", \"id\":\"SZ\", \"projects\":14, \"budget\":2676.67, \"flag\":\"/images/flags/sz.png\"}, \"AG\":{\"country\":\"Antigua and Barbuda\", \"id\":\"AG\", \"projects\":11, \"budget\":2676.67, \"flag\":\"/images/flags/ag.png\"}, \"ZA\":{\"country\":\"South Africa\", \"id\":\"ZA\", \"projects\":52, \"budget\":12656711.58, \"flag\":\"/images/flags/za.png\"}, \"SB\":{\"country\":\"Solomon Islands\", \"id\":\"SB\", \"projects\":11, \"budget\":2676.67, \"flag\":\"/images/flags/sb.png\"}, \"VU\":{\"country\":\"Vanuatu\", \"id\":\"VU\", \"projects\":11, \"budget\":2676.67, \"flag\":\"/images/flags/vu.png\"}, \"FJ\":{\"country\":\"Fiji\", \"id\":\"FJ\", \"projects\":13, \"budget\":2676.67, \"flag\":\"/images/flags/fj.png\"}, \"KI\":{\"country\":\"Kiribati\", \"id\":\"KI\", \"projects\":11, \"budget\":2676.67, \"flag\":\"/images/flags/ki.png\"}, \"TO\":{\"country\":\"Tonga\", \"id\":\"TO\", \"projects\":11, \"budget\":2676.67, \"flag\":\"/images/flags/to.png\"}, \"TV\":{\"country\":\"Tuvalu\", \"id\":\"TV\", \"projects\":11, \"budget\":2676.67, \"flag\":\"/images/flags/tv.png\"}, \"WS\":{\"country\":\"Samoa\", \"id\":\"WS\", \"projects\":12, \"budget\":2676.67, \"flag\":\"/images/flags/ws.png\"}, \"PG\":{\"country\":\"Papua New Guinea\", \"id\":\"PG\", \"projects\":13, \"budget\":1402668.67, \"flag\":\"/images/flags/pg.png\"}, \"GN\":{\"country\":\"Guinea\", \"id\":\"GN\", \"projects\":13, \"budget\":2676.67, \"flag\":\"/images/flags/gn.png\"}, \"MY\":{\"country\":\"Malaysia\", \"id\":\"MY\", \"projects\":32, \"budget\":822647.99, \"flag\":\"/images/flags/my.png\"}, \"SL\":{\"country\":\"Sierra Leone\", \"id\":\"SL\", \"projects\":33, \"budget\":22186312.67, \"flag\":\"/images/flags/sl.png\"}, \"YE\":{\"country\":\"Yemen\", \"id\":\"YE\", \"projects\":25, \"budget\":65259341.45, \"flag\":\"/images/flags/ye.png\"}, \"BT\":{\"country\":\"Bhutan\", \"id\":\"BT\", \"projects\":13, \"budget\":2676.67, \"flag\":\"/images/flags/bt.png\"}, \"CG\":{\"country\":\"Congo (the)\", \"id\":\"CG\", \"projects\":15, \"budget\":808260.37, \"flag\":\"/images/flags/cg.png\"}, \"NG\":{\"country\":\"Nigeria\", \"id\":\"NG\", \"projects\":45, \"budget\":129174215.44, \"flag\":\"/images/flags/ng.png\"}, \"TJ\":{\"country\":\"Tajikistan\", \"id\":\"TJ\", \"projects\":15, \"budget\":908241.46, \"flag\":\"/images/flags/tj.png\"}, \"MM\":{\"country\":\"Myanmar\", \"id\":\"MM\", \"projects\":36, \"budget\":69973839.49, \"flag\":\"/images/flags/mm.png\"}, \"KM\":{\"country\":\"Comoros (the)\", \"id\":\"KM\", \"projects\":13, \"budget\":28892.47, \"flag\":\"/images/flags/km.png\"}, \"TL\":{\"country\":\"Timor-Leste\", \"id\":\"TL\", \"projects\":14, \"budget\":256829.71, \"flag\":\"/images/flags/tl.png\"}, \"GY\":{\"country\":\"Guyana\", \"id\":\"GY\", \"projects\":13, \"budget\":915671.53, \"flag\":\"/images/flags/gy.png\"}, \"CI\":{\"country\":\"Côte d'Ivoire\", \"id\":\"CI\", \"projects\":14, \"budget\":1002676.67, \"flag\":\"/images/flags/ci.png\"}, \"MA\":{\"country\":\"Morocco\", \"id\":\"MA\", \"projects\":16, \"budget\":31950.98, \"flag\":\"/images/flags/ma.png\"}, \"PK\":{\"country\":\"Pakistan\", \"id\":\"PK\", \"projects\":36, \"budget\":46841178.71, \"flag\":\"/images/flags/pk.png\"}, \"BJ\":{\"country\":\"Benin\", \"id\":\"BJ\", \"projects\":14, \"budget\":2676.67, \"flag\":\"/images/flags/bj.png\"}, \"CD\":{\"country\":\"Congo (the Democratic Republic of the)\", \"id\":\"CD\", \"projects\":26, \"budget\":45942759.71, \"flag\":\"/images/flags/cd.png\"}, \"CV\":{\"country\":\"Cabo Verde\", \"id\":\"CV\", \"projects\":12, \"budget\":3550.53, \"flag\":\"/images/flags/cv.png\"}, \"SN\":{\"country\":\"Senegal\", \"id\":\"SN\", \"projects\":18, \"budget\":3550.53, \"flag\":\"/images/flags/sn.png\"}, \"SG\":{\"country\":\"Singapore\", \"id\":\"SG\", \"projects\":10, \"budget\":2676.67, \"flag\":\"/images/flags/sg.png\"}, \"EG\":{\"country\":\"Egypt\", \"id\":\"EG\", \"projects\":22, \"budget\":1404353.71, \"flag\":\"/images/flags/eg.png\"}, \"BF\":{\"country\":\"Burkina Faso\", \"id\":\"BF\", \"projects\":15, \"budget\":2676.67, \"flag\":\"/images/flags/bf.png\"}, \"JO\":{\"country\":\"Jordan\", \"id\":\"JO\", \"projects\":35, \"budget\":39335139.71, \"flag\":\"/images/flags/jo.png\"}, \"TR\":{\"country\":\"Türkiye\", \"id\":\"TR\", \"projects\":32, \"budget\":22802687.67, \"flag\":\"/images/flags/tr.png\"}, \"CL\":{\"country\":\"Chile\", \"id\":\"CL\", \"projects\":2, \"budget\":0.0, \"flag\":\"/images/flags/cl.png\"}, \"KZ\":{\"country\":\"Kazakhstan\", \"id\":\"KZ\", \"projects\":15, \"budget\":2676.67, \"flag\":\"/images/flags/kz.png\"}, \"DZ\":{\"country\":\"Algeria\", \"id\":\"DZ\", \"projects\":14, \"budget\":2676.67, \"flag\":\"/images/flags/dz.png\"}, \"LY\":{\"country\":\"Libya\", \"id\":\"LY\", \"projects\":15, \"budget\":2676.67, \"flag\":\"/images/flags/ly.png\"}, \"TN\":{\"country\":\"Tunisia\", \"id\":\"TN\", \"projects\":16, \"budget\":256829.71, \"flag\":\"/images/flags/tn.png\"}, \"BI\":{\"country\":\"Burundi\", \"id\":\"BI\", \"projects\":12, \"budget\":2676.67, \"flag\":\"/images/flags/bi.png\"}, \"MU\":{\"country\":\"Mauritius\", \"id\":\"MU\", \"projects\":14, \"budget\":388229.67, \"flag\":\"/images/flags/mu.png\"}, \"ER\":{\"country\":\"Eritrea\", \"id\":\"ER\", \"projects\":12, \"budget\":2676.67, \"flag\":\"/images/flags/er.png\"}, \"DJ\":{\"country\":\"Djibouti\", \"id\":\"DJ\", \"projects\":11, \"budget\":2676.67, \"flag\":\"/images/flags/dj.png\"}, \"SD\":{\"country\":\"Sudan (the)\", \"id\":\"SD\", \"projects\":22, \"budget\":9700324.87, \"flag\":\"/images/flags/sd.png\"}, \"CF\":{\"country\":\"Central African Republic (the)\", \"id\":\"CF\", \"projects\":13, \"budget\":2676.67, \"flag\":\"/images/flags/cf.png\"}, \"TD\":{\"country\":\"Chad\", \"id\":\"TD\", \"projects\":15, \"budget\":1502676.67, \"flag\":\"/images/flags/td.png\"}, \"GA\":{\"country\":\"Gabon\", \"id\":\"GA\", \"projects\":11, \"budget\":2676.67, \"flag\":\"/images/flags/ga.png\"}, \"GQ\":{\"country\":\"Equatorial Guinea\", \"id\":\"GQ\", \"projects\":11, \"budget\":2676.67, \"flag\":\"/images/flags/gq.png\"}, \"ST\":{\"country\":\"Sao Tome and Principe\", \"id\":\"ST\", \"projects\":11, \"budget\":2676.67, \"flag\":\"/images/flags/st.png\"}, \"LS\":{\"country\":\"Lesotho\", \"id\":\"LS\", \"projects\":12, \"budget\":2676.67, \"flag\":\"/images/flags/ls.png\"}, \"GM\":{\"country\":\"Gambia (the)\", \"id\":\"GM\", \"projects\":11, \"budget\":2676.67, \"flag\":\"/images/flags/gm.png\"}, \"GW\":{\"country\":\"Guinea-Bissau\", \"id\":\"GW\", \"projects\":12, \"budget\":2676.67, \"flag\":\"/images/flags/gw.png\"}, \"MR\":{\"country\":\"Mauritania\", \"id\":\"MR\", \"projects\":12, \"budget\":2676.67, \"flag\":\"/images/flags/mr.png\"}, \"TG\":{\"country\":\"Togo\", \"id\":\"TG\", \"projects\":12, \"budget\":2676.67, \"flag\":\"/images/flags/tg.png\"}, \"CU\":{\"country\":\"Cuba\", \"id\":\"CU\", \"projects\":13, \"budget\":2676.67, \"flag\":\"/images/flags/cu.png\"}, \"DO\":{\"country\":\"Dominican Republic (the)\", \"id\":\"DO\", \"projects\":11, \"budget\":2676.67, \"flag\":\"/images/flags/do.png\"}, \"HT\":{\"country\":\"Haiti\", \"id\":\"HT\", \"projects\":13, \"budget\":12875924.67, \"flag\":\"/images/flags/ht.png\"}, \"JM\":{\"country\":\"Jamaica\", \"id\":\"JM\", \"projects\":13, \"budget\":2002696.67, \"flag\":\"/images/flags/jm.png\"}, \"DM\":{\"country\":\"Dominica\", \"id\":\"DM\", \"projects\":12, \"budget\":2676.67, \"flag\":\"/images/flags/dm.png\"}, \"GD\":{\"country\":\"Grenada\", \"id\":\"GD\", \"projects\":11, \"budget\":2676.67, \"flag\":\"/images/flags/gd.png\"}, \"LC\":{\"country\":\"Saint Lucia\", \"id\":\"LC\", \"projects\":11, \"budget\":2676.67, \"flag\":\"/images/flags/lc.png\"}, \"VC\":{\"country\":\"Saint Vincent and the Grenadines\", \"id\":\"VC\", \"projects\":11, \"budget\":2676.67, \"flag\":\"/images/flags/vc.png\"}, \"AR\":{\"country\":\"Argentina\", \"id\":\"AR\", \"projects\":16, \"budget\":2676.67, \"flag\":\"/images/flags/ar.png\"}, \"PY\":{\"country\":\"Paraguay\", \"id\":\"PY\", \"projects\":11, \"budget\":2676.67, \"flag\":\"/images/flags/py.png\"}, \"SR\":{\"country\":\"Suriname\", \"id\":\"SR\", \"projects\":11, \"budget\":2676.67, \"flag\":\"/images/flags/sr.png\"}, \"VE\":{\"country\":\"Venezuela (Bolivarian Republic of)\", \"id\":\"VE\", \"projects\":13, \"budget\":2676.67, \"flag\":\"/images/flags/ve.png\"}, \"KP\":{\"country\":\"Korea (the Democratic People's Republic of)\", \"id\":\"KP\", \"projects\":11, \"budget\":2676.67, \"flag\":\"/images/flags/kp.png\"}, \"IR\":{\"country\":\"Iran (Islamic Republic of)\", \"id\":\"IR\", \"projects\":13, \"budget\":185086.15, \"flag\":\"/images/flags/ir.png\"}, \"IQ\":{\"country\":\"Iraq\", \"id\":\"IQ\", \"projects\":23, \"budget\":12162709.87, \"flag\":\"/images/flags/iq.png\"}, \"LB\":{\"country\":\"Lebanon\", \"id\":\"LB\", \"projects\":22, \"budget\":66126156.67, \"flag\":\"/images/flags/lb.png\"}, \"AZ\":{\"country\":\"Azerbaijan\", \"id\":\"AZ\", \"projects\":12, \"budget\":2676.67, \"flag\":\"/images/flags/az.png\"}, \"TM\":{\"country\":\"Turkmenistan\", \"id\":\"TM\", \"projects\":11, \"budget\":2676.67, \"flag\":\"/images/flags/tm.png\"}, \"UZ\":{\"country\":\"Uzbekistan\", \"id\":\"UZ\", \"projects\":13, \"budget\":2676.67, \"flag\":\"/images/flags/uz.png\"}, \"AF\":{\"country\":\"Afghanistan\", \"id\":\"AF\", \"projects\":25, \"budget\":182947028.91, \"flag\":\"/images/flags/af.png\"}, \"MV\":{\"country\":\"Maldives\", \"id\":\"MV\", \"projects\":11, \"budget\":2676.67, \"flag\":\"/images/flags/mv.png\"}, \"XK\":{\"country\":\"Kosovo\", \"id\":\"XK\", \"projects\":12, \"budget\":2676.67, \"flag\":\"/images/flags/xk.png\"}, \"RS\":{\"country\":\"Serbia\", \"id\":\"RS\", \"projects\":14, \"budget\":2676.67, \"flag\":\"/images/flags/rs.png\"}, \"BA\":{\"country\":\"Bosnia and Herzegovina\", \"id\":\"BA\", \"projects\":14, \"budget\":2563559.83, \"flag\":\"/images/flags/ba.png\"}, \"ME\":{\"country\":\"Montenegro\", \"id\":\"ME\", \"projects\":12, \"budget\":2676.67, \"flag\":\"/images/flags/me.png\"}, \"MK\":{\"country\":\"North Macedonia\", \"id\":\"MK\", \"projects\":13, \"budget\":2676.67, \"flag\":\"/images/flags/mk.png\"}, \"UA\":{\"country\":\"Ukraine\", \"id\":\"UA\", \"projects\":15, \"budget\":232668.67, \"flag\":\"/images/flags/ua.png\"}, \"BY\":{\"country\":\"Belarus\", \"id\":\"BY\", \"projects\":11, \"budget\":2676.67, \"flag\":\"/images/flags/by.png\"}, \"MD\":{\"country\":\"Moldova (the Republic of)\", \"id\":\"MD\", \"projects\":14, \"budget\":4503661.95, \"flag\":\"/images/flags/md.png\"}, \"NR\":{\"country\":\"Nauru\", \"id\":\"NR\", \"projects\":11, \"budget\":2676.67, \"flag\":\"/images/flags/nr.png\"}, \"MH\":{\"country\":\"Marshall Islands (the)\", \"id\":\"MH\", \"projects\":11, \"budget\":2676.67, \"flag\":\"/images/flags/mh.png\"}, \"PW\":{\"country\":\"Palau\", \"id\":\"PW\", \"projects\":11, \"budget\":2676.67, \"flag\":\"/images/flags/pw.png\"}, \"NU\":{\"country\":\"Niue\", \"id\":\"NU\", \"projects\":11, \"budget\":2676.67, \"flag\":\"/images/flags/nu.png\"}, \"TK\":{\"country\":\"Tokelau\", \"id\":\"TK\", \"projects\":11, \"budget\":2676.67, \"flag\":\"/images/flags/tk.png\"}, \"WF\":{\"country\":\"Wallis and Futuna\", \"id\":\"WF\", \"projects\":11, \"budget\":2676.67, \"flag\":\"/images/flags/wf.png\"}, \"YT\":{\"country\":\"Mayotte\", \"id\":\"YT\", \"projects\":9, \"budget\":2676.67, \"flag\":\"/images/flags/yt.png\"}, \"BS\":{\"country\":\"Bahamas (the)\", \"id\":\"BS\", \"projects\":9, \"budget\":2676.67, \"flag\":\"/images/flags/bs.png\"}, \"BB\":{\"country\":\"Barbados\", \"id\":\"BB\", \"projects\":9, \"budget\":2676.67, \"flag\":\"/images/flags/bb.png\"}, \"AN\":{\"country\":\"Netherlands Antilles\", \"id\":\"AN\", \"projects\":9, \"budget\":2676.67, \"flag\":\"/images/flags/an.png\"}, \"AW\":{\"country\":\"Aruba\", \"id\":\"AW\", \"projects\":9, \"budget\":2676.67, \"flag\":\"/images/flags/aw.png\"}, \"TT\":{\"country\":\"Trinidad and Tobago\", \"id\":\"TT\", \"projects\":9, \"budget\":2676.67, \"flag\":\"/images/flags/tt.png\"}, \"AI\":{\"country\":\"Anguilla\", \"id\":\"AI\", \"projects\":9, \"budget\":2676.67, \"flag\":\"/images/flags/ai.png\"}, \"KN\":{\"country\":\"Saint Kitts and Nevis\", \"id\":\"KN\", \"projects\":9, \"budget\":2676.67, \"flag\":\"/images/flags/kn.png\"}, \"KY\":{\"country\":\"Cayman Islands (the)\", \"id\":\"KY\", \"projects\":9, \"budget\":2676.67, \"flag\":\"/images/flags/ky.png\"}, \"TC\":{\"country\":\"Turks and Caicos Islands (the)\", \"id\":\"TC\", \"projects\":9, \"budget\":2676.67, \"flag\":\"/images/flags/tc.png\"}, \"VG\":{\"country\":\"Virgin Islands (British)\", \"id\":\"VG\", \"projects\":9, \"budget\":2676.67, \"flag\":\"/images/flags/vg.png\"}, \"FK\":{\"country\":\"Falkland Islands (the) Malvinas\", \"id\":\"FK\", \"projects\":9, \"budget\":2676.67, \"flag\":\"/images/flags/fk.png\"}, \"BN\":{\"country\":\"Brunei Darussalam\", \"id\":\"BN\", \"projects\":9, \"budget\":2676.67, \"flag\":\"/images/flags/bn.png\"}, \"TW\":{\"country\":\"Taiwan (Province of China)\", \"id\":\"TW\", \"projects\":9, \"budget\":2676.67, \"flag\":\"/images/flags/tw.png\"}, \"HK\":{\"country\":\"Hong Kong\", \"id\":\"HK\", \"projects\":9, \"budget\":2676.67, \"flag\":\"/images/flags/hk.png\"}, \"KR\":{\"country\":\"Korea (the Republic of)\", \"id\":\"KR\", \"projects\":9, \"budget\":2676.67, \"flag\":\"/images/flags/kr.png\"}, \"MO\":{\"country\":\"Macao\", \"id\":\"MO\", \"projects\":9, \"budget\":2676.67, \"flag\":\"/images/flags/mo.png\"}, \"BH\":{\"country\":\"Bahrain\", \"id\":\"BH\", \"projects\":9, \"budget\":2676.67, \"flag\":\"/images/flags/bh.png\"}, \"IL\":{\"country\":\"Israel\", \"id\":\"IL\", \"projects\":9, \"budget\":2676.67, \"flag\":\"/images/flags/il.png\"}, \"KW\":{\"country\":\"Kuwait\", \"id\":\"KW\", \"projects\":9, \"budget\":2676.67, \"flag\":\"/images/flags/kw.png\"}, \"OM\":{\"country\":\"Oman\", \"id\":\"OM\", \"projects\":9, \"budget\":2676.67, \"flag\":\"/images/flags/om.png\"}, \"QA\":{\"country\":\"Qatar\", \"id\":\"QA\", \"projects\":9, \"budget\":2676.67, \"flag\":\"/images/flags/qa.png\"}, \"SA\":{\"country\":\"Saudi Arabia\", \"id\":\"SA\", \"projects\":9, \"budget\":2676.67, \"flag\":\"/images/flags/sa.png\"}, \"AE\":{\"country\":\"United Arab Emirates (the)\", \"id\":\"AE\", \"projects\":9, \"budget\":2676.67, \"flag\":\"/images/flags/ae.png\"}, \"CY\":{\"country\":\"Cyprus\", \"id\":\"CY\", \"projects\":9, \"budget\":2676.67, \"flag\":\"/images/flags/cy.png\"}, \"GI\":{\"country\":\"Gibraltar\", \"id\":\"GI\", \"projects\":9, \"budget\":2676.67, \"flag\":\"/images/flags/gi.png\"}, \"MT\":{\"country\":\"Malta\", \"id\":\"MT\", \"projects\":9, \"budget\":2676.67, \"flag\":\"/images/flags/mt.png\"}, \"SI\":{\"country\":\"Slovenia\", \"id\":\"SI\", \"projects\":9, \"budget\":2676.67, \"flag\":\"/images/flags/si.png\"}, \"HR\":{\"country\":\"Croatia\", \"id\":\"HR\", \"projects\":9, \"budget\":2676.67, \"flag\":\"/images/flags/hr.png\"}, \"NC\":{\"country\":\"New Caledonia\", \"id\":\"NC\", \"projects\":9, \"budget\":2676.67, \"flag\":\"/images/flags/nc.png\"}, \"MP\":{\"country\":\"Northern Mariana Islands (the)\", \"id\":\"MP\", \"projects\":9, \"budget\":2676.67, \"flag\":\"/images/flags/mp.png\"}, \"PF\":{\"country\":\"French Polynesia\", \"id\":\"PF\", \"projects\":9, \"budget\":2676.67, \"flag\":\"/images/flags/pf.png\"}, \"SC\":{\"country\":\"Seychelles\", \"id\":\"SC\", \"projects\":0, \"budget\":0.0, \"flag\":\"/images/flags/sc.png\"}, \"UY\":{\"country\":\"Uruguay\", \"id\":\"UY\", \"projects\":1, \"budget\":0.0, \"flag\":\"/images/flags/uy.png\"}, \"GB\":{\"country\":\"United Kingdom of Great Britain and Northern Ireland (the)\", \"id\":\"GB\", \"projects\":5, \"budget\":1711774.0, \"flag\":\"/images/flags/gb.png\"}, \"GR\":{\"country\":\"Greece\", \"id\":\"GR\", \"projects\":0, \"budget\":0.0, \"flag\":\"/images/flags/gr.png\"}, \"JP\":{\"country\":\"Japan\", \"id\":\"JP\", \"projects\":0, \"budget\":0.0, \"flag\":\"/images/flags/jp.png\"}, \"RU\":{\"country\":\"Russian Federation (the)\", \"id\":\"RU\", \"projects\":0, \"budget\":0.0, \"flag\":\"/images/flags/ru.png\"}, \"AS\":{\"country\":\"American Samoa\", \"id\":\"AS\", \"projects\":0, \"budget\":0.0, \"flag\":\"/images/flags/as.png\"}}",{"PH":{"country":"Philippines (the)","id":"PH","projects":35,"budget":845368.35,"flag":"/images/flags/ph.png"},"IN":{"country":"India","id":"IN","projects":51,"budget":28578966.75,"flag":"/images/flags/in.png"},"GH":{"country":"Ghana","id":"GH","projects":39,"budget":17676308.6,"flag":"/images/flags/gh.png"},"RW":{"country":"Rwanda","id":"RW","projects":23,"budget":31340724.38,"flag":"/images/flags/rw.png"},"KE":{"country":"Kenya","id":"KE","projects":53,"budget":83292537.39,"flag":"/images/flags/ke.png"},"NA":{"country":"Namibia","id":"NA","projects":18,"budget":2676.67,"flag":"/images/flags/na.png"},"SY":{"country":"Syrian Arab Republic (the)","id":"SY","projects":25,"budget":87397616.71,"flag":"/images/flags/sy.png"},"VN":{"country":"Viet Nam","id":"VN","projects":37,"budget":1923977.83,"flag":"/images/flags/vn.png"},"AL":{"country":"Albania","id":"AL","projects":14,"budget":2676.67,"flag":"/images/flags/al.png"},"EC":{"country":"Ecuador","id":"EC","projects":17,"budget":2676.67,"flag":"/images/flags/ec.png"},"CR":{"country":"Costa Rica","id":"CR","projects":12,"budget":2676.67,"flag":"/images/flags/cr.png"},"NI":{"country":"Nicaragua","id":"NI","projects":15,"budget":25397.03,"flag":"/images/flags/ni.png"},"SV":{"country":"El Salvador","id":"SV","projects":14,"budget":2676.67,"flag":"/images/flags/sv.png"},"CO":{"country":"Colombia","id":"CO","projects":32,"budget":14725580.03,"flag":"/images/flags/co.png"},"PA":{"country":"Panama","id":"PA","projects":12,"budget":2676.67,"flag":"/images/flags/pa.png"},"HN":{"country":"Honduras","id":"HN","projects":14,"budget":2676.67,"flag":"/images/flags/hn.png"},"MX":{"country":"Mexico","id":"MX","projects":32,"budget":2676.67,"flag":"/images/flags/mx.png"},"PE":{"country":"Peru","id":"PE","projects":26,"budget":2676.67,"flag":"/images/flags/pe.png"},"GT":{"country":"Guatemala","id":"GT","projects":14,"budget":2676.67,"flag":"/images/flags/gt.png"},"ID":{"country":"Indonesia","id":"ID","projects":50,"budget":8449464.02,"flag":"/images/flags/id.png"},"ET":{"country":"Ethiopia","id":"ET","projects":42,"budget":97671333.25,"flag":"/images/flags/et.png"},"ZM":{"country":"Zambia","id":"ZM","projects":33,"budget":22081302.38,"flag":"/images/flags/zm.png"},"MW":{"country":"Malawi","id":"MW","projects":36,"budget":24499704.77,"flag":"/images/flags/mw.png"},"BZ":{"country":"Belize","id":"BZ","projects":12,"budget":2676.67,"flag":"/images/flags/bz.png"},"CN":{"country":"China","id":"CN","projects":39,"budget":102176.67,"flag":"/images/flags/cn.png"},"CM":{"country":"Cameroon","id":"CM","projects":25,"budget":2676.67,"flag":"/images/flags/cm.png"},"BW":{"country":"Botswana","id":"BW","projects":15,"budget":2676.67,"flag":"/images/flags/bw.png"},"MZ":{"country":"Mozambique","id":"MZ","projects":35,"budget":56784115.58,"flag":"/images/flags/mz.png"},"UG":{"country":"Uganda","id":"UG","projects":42,"budget":25718500.14,"flag":"/images/flags/ug.png"},"KG":{"country":"Kyrgyzstan","id":"KG","projects":13,"budget":7787740.67,"flag":"/images/flags/kg.png"},"LA":{"country":"Lao People's Democratic Republic (the)","id":"LA","projects":18,"budget":2676.67,"flag":"/images/flags/la.png"},"MG":{"country":"Madagascar","id":"MG","projects":22,"budget":2222708.56,"flag":"/images/flags/mg.png"},"MN":{"country":"Mongolia","id":"MN","projects":13,"budget":2676.67,"flag":"/images/flags/mn.png"},"ML":{"country":"Mali","id":"ML","projects":17,"budget":2602668.67,"flag":"/images/flags/ml.png"},"BR":{"country":"Brazil","id":"BR","projects":43,"budget":13124547.99,"flag":"/images/flags/br.png"},"LK":{"country":"Sri Lanka","id":"LK","projects":21,"budget":28892.47,"flag":"/images/flags/lk.png"},"MS":{"country":"Montserrat","id":"MS","projects":20,"budget":78459810.67,"flag":"/images/flags/ms.png"},"PN":{"country":"Pitcairn","id":"PN","projects":3,"budget":0.0,"flag":"/images/flags/pn.png"},"SH":{"country":"Saint Helena, Ascension and Tristan da Cunha","id":"SH","projects":19,"budget":6010529.67,"flag":"/images/flags/sh.png"},"AO":{"country":"Angola","id":"AO","projects":14,"budget":2676.67,"flag":"/images/flags/ao.png"},"ZW":{"country":"Zimbabwe","id":"ZW","projects":33,"budget":20593388.23,"flag":"/images/flags/zw.png"},"BD":{"country":"Bangladesh","id":"BD","projects":37,"budget":55209097.91,"flag":"/images/flags/bd.png"},"AM":{"country":"Armenia","id":"AM","projects":16,"budget":4371280.03,"flag":"/images/flags/am.png"},"GE":{"country":"Georgia","id":"GE","projects":17,"budget":4371280.03,"flag":"/images/flags/ge.png"},"BO":{"country":"Bolivia (Plurinational State of)","id":"BO","projects":15,"budget":2676.67,"flag":"/images/flags/bo.png"},"KH":{"country":"Cambodia","id":"KH","projects":20,"budget":299648.85,"flag":"/images/flags/kh.png"},"TH":{"country":"Thailand","id":"TH","projects":32,"budget":256829.71,"flag":"/images/flags/th.png"},"LR":{"country":"Liberia","id":"LR","projects":20,"budget":946693.56,"flag":"/images/flags/lr.png"},"FM":{"country":"Micronesia (Federated States of)","id":"FM","projects":12,"budget":2676.67,"flag":"/images/flags/fm.png"},"NP":{"country":"Nepal","id":"NP","projects":40,"budget":56459776.71,"flag":"/images/flags/np.png"},"NE":{"country":"Niger (the)","id":"NE","projects":17,"budget":76938.67,"flag":"/images/flags/ne.png"},"PS":{"country":"Palestine, State of","id":"PS","projects":19,"budget":6428046.67,"flag":"/images/flags/ps.png"},"SO":{"country":"Somalia","id":"SO","projects":28,"budget":129598264.75,"flag":"/images/flags/so.png"},"SS":{"country":"South Sudan","id":"SS","projects":26,"budget":51860842.91,"flag":"/images/flags/ss.png"},"TZ":{"country":"Tanzania, the United Republic of","id":"TZ","projects":41,"budget":27829129.09,"flag":"/images/flags/tz.png"},"SZ":{"country":"Eswatini","id":"SZ","projects":14,"budget":2676.67,"flag":"/images/flags/sz.png"},"AG":{"country":"Antigua and Barbuda","id":"AG","projects":11,"budget":2676.67,"flag":"/images/flags/ag.png"},"ZA":{"country":"South Africa","id":"ZA","projects":52,"budget":12656711.58,"flag":"/images/flags/za.png"},"SB":{"country":"Solomon Islands","id":"SB","projects":11,"budget":2676.67,"flag":"/images/flags/sb.png"},"VU":{"country":"Vanuatu","id":"VU","projects":11,"budget":2676.67,"flag":"/images/flags/vu.png"},"FJ":{"country":"Fiji","id":"FJ","projects":13,"budget":2676.67,"flag":"/images/flags/fj.png"},"KI":{"country":"Kiribati","id":"KI","projects":11,"budget":2676.67,"flag":"/images/flags/ki.png"},"TO":{"country":"Tonga","id":"TO","projects":11,"budget":2676.67,"flag":"/images/flags/to.png"},"TV":{"country":"Tuvalu","id":"TV","projects":11,"budget":2676.67,"flag":"/images/flags/tv.png"},"WS":{"country":"Samoa","id":"WS","projects":12,"budget":2676.67,"flag":"/images/flags/ws.png"},"PG":{"country":"Papua New Guinea","id":"PG","projects":13,"budget":1402668.67,"flag":"/images/flags/pg.png"},"GN":{"country":"Guinea","id":"GN","projects":13,"budget":2676.67,"flag":"/images/flags/gn.png"},"MY":{"country":"Malaysia","id":"MY","projects":32,"budget":822647.99,"flag":"/images/flags/my.png"},"SL":{"country":"Sierra Leone","id":"SL","projects":33,"budget":22186312.67,"flag":"/images/flags/sl.png"},"YE":{"country":"Yemen","id":"YE","projects":25,"budget":65259341.45,"flag":"/images/flags/ye.png"},"BT":{"country":"Bhutan","id":"BT","projects":13,"budget":2676.67,"flag":"/images/flags/bt.png"},"CG":{"country":"Congo (the)","id":"CG","projects":15,"budget":808260.37,"flag":"/images/flags/cg.png"},"NG":{"country":"Nigeria","id":"NG","projects":45,"budget":129174215.44,"flag":"/images/flags/ng.png"},"TJ":{"country":"Tajikistan","id":"TJ","projects":15,"budget":908241.46,"flag":"/images/flags/tj.png"},"MM":{"country":"Myanmar","id":"MM","projects":36,"budget":69973839.49,"flag":"/images/flags/mm.png"},"KM":{"country":"Comoros (the)","id":"KM","projects":13,"budget":28892.47,"flag":"/images/flags/km.png"},"TL":{"country":"Timor-Leste","id":"TL","projects":14,"budget":256829.71,"flag":"/images/flags/tl.png"},"GY":{"country":"Guyana","id":"GY","projects":13,"budget":915671.53,"flag":"/images/flags/gy.png"},"CI":{"country":"Côte d'Ivoire","id":"CI","projects":14,"budget":1002676.67,"flag":"/images/flags/ci.png"},"MA":{"country":"Morocco","id":"MA","projects":16,"budget":31950.98,"flag":"/images/flags/ma.png"},"PK":{"country":"Pakistan","id":"PK","projects":36,"budget":46841178.71,"flag":"/images/flags/pk.png"},"BJ":{"country":"Benin","id":"BJ","projects":14,"budget":2676.67,"flag":"/images/flags/bj.png"},"CD":{"country":"Congo (the Democratic Republic of the)","id":"CD","projects":26,"budget":45942759.71,"flag":"/images/flags/cd.png"},"CV":{"country":"Cabo Verde","id":"CV","projects":12,"budget":3550.53,"flag":"/images/flags/cv.png"},"SN":{"country":"Senegal","id":"SN","projects":18,"budget":3550.53,"flag":"/images/flags/sn.png"},"SG":{"country":"Singapore","id":"SG","projects":10,"budget":2676.67,"flag":"/images/flags/sg.png"},"EG":{"country":"Egypt","id":"EG","projects":22,"budget":1404353.71,"flag":"/images/flags/eg.png"},"BF":{"country":"Burkina Faso","id":"BF","projects":15,"budget":2676.67,"flag":"/images/flags/bf.png"},"JO":{"country":"Jordan","id":"JO","projects":35,"budget":39335139.71,"flag":"/images/flags/jo.png"},"TR":{"country":"Türkiye","id":"TR","projects":32,"budget":22802687.67,"flag":"/images/flags/tr.png"},"CL":{"country":"Chile","id":"CL","projects":2,"budget":0.0,"flag":"/images/flags/cl.png"},"KZ":{"country":"Kazakhstan","id":"KZ","projects":15,"budget":2676.67,"flag":"/images/flags/kz.png"},"DZ":{"country":"Algeria","id":"DZ","projects":14,"budget":2676.67,"flag":"/images/flags/dz.png"},"LY":{"country":"Libya","id":"LY","projects":15,"budget":2676.67,"flag":"/images/flags/ly.png"},"TN":{"country":"Tunisia","id":"TN","projects":16,"budget":256829.71,"flag":"/images/flags/tn.png"},"BI":{"country":"Burundi","id":"BI","projects":12,"budget":2676.67,"flag":"/images/flags/bi.png"},"MU":{"country":"Mauritius","id":"MU","projects":14,"budget":388229.67,"flag":"/images/flags/mu.png"},"ER":{"country":"Eritrea","id":"ER","projects":12,"budget":2676.67,"flag":"/images/flags/er.png"},"DJ":{"country":"Djibouti","id":"DJ","projects":11,"budget":2676.67,"flag":"/images/flags/dj.png"},"SD":{"country":"Sudan (the)","id":"SD","projects":22,"budget":9700324.87,"flag":"/images/flags/sd.png"},"CF":{"country":"Central African Republic (the)","id":"CF","projects":13,"budget":2676.67,"flag":"/images/flags/cf.png"},"TD":{"country":"Chad","id":"TD","projects":15,"budget":1502676.67,"flag":"/images/flags/td.png"},"GA":{"country":"Gabon","id":"GA","projects":11,"budget":2676.67,"flag":"/images/flags/ga.png"},"GQ":{"country":"Equatorial Guinea","id":"GQ","projects":11,"budget":2676.67,"flag":"/images/flags/gq.png"},"ST":{"country":"Sao Tome and Principe","id":"ST","projects":11,"budget":2676.67,"flag":"/images/flags/st.png"},"LS":{"country":"Lesotho","id":"LS","projects":12,"budget":2676.67,"flag":"/images/flags/ls.png"},"GM":{"country":"Gambia (the)","id":"GM","projects":11,"budget":2676.67,"flag":"/images/flags/gm.png"},"GW":{"country":"Guinea-Bissau","id":"GW","projects":12,"budget":2676.67,"flag":"/images/flags/gw.png"},"MR":{"country":"Mauritania","id":"MR","projects":12,"budget":2676.67,"flag":"/images/flags/mr.png"},"TG":{"country":"Togo","id":"TG","projects":12,"budget":2676.67,"flag":"/images/flags/tg.png"},"CU":{"country":"Cuba","id":"CU","projects":13,"budget":2676.67,"flag":"/images/flags/cu.png"},"DO":{"country":"Dominican Republic (the)","id":"DO","projects":11,"budget":2676.67,"flag":"/images/flags/do.png"},"HT":{"country":"Haiti","id":"HT","projects":13,"budget":12875924.67,"flag":"/images/flags/ht.png"},"JM":{"country":"Jamaica","id":"JM","projects":13,"budget":2002696.67,"flag":"/images/flags/jm.png"},"DM":{"country":"Dominica","id":"DM","projects":12,"budget":2676.67,"flag":"/images/flags/dm.png"},"GD":{"country":"Grenada","id":"GD","projects":11,"budget":2676.67,"flag":"/images/flags/gd.png"},"LC":{"country":"Saint Lucia","id":"LC","projects":11,"budget":2676.67,"flag":"/images/flags/lc.png"},"VC":{"country":"Saint Vincent and the Grenadines","id":"VC","projects":11,"budget":2676.67,"flag":"/images/flags/vc.png"},"AR":{"country":"Argentina","id":"AR","projects":16,"budget":2676.67,"flag":"/images/flags/ar.png"},"PY":{"country":"Paraguay","id":"PY","projects":11,"budget":2676.67,"flag":"/images/flags/py.png"},"SR":{"country":"Suriname","id":"SR","projects":11,"budget":2676.67,"flag":"/images/flags/sr.png"},"VE":{"country":"Venezuela (Bolivarian Republic of)","id":"VE","projects":13,"budget":2676.67,"flag":"/images/flags/ve.png"},"KP":{"country":"Korea (the Democratic People's Republic of)","id":"KP","projects":11,"budget":2676.67,"flag":"/images/flags/kp.png"},"IR":{"country":"Iran (Islamic Republic of)","id":"IR","projects":13,"budget":185086.15,"flag":"/images/flags/ir.png"},"IQ":{"country":"Iraq","id":"IQ","projects":23,"budget":12162709.87,"flag":"/images/flags/iq.png"},"LB":{"country":"Lebanon","id":"LB","projects":22,"budget":66126156.67,"flag":"/images/flags/lb.png"},"AZ":{"country":"Azerbaijan","id":"AZ","projects":12,"budget":2676.67,"flag":"/images/flags/az.png"},"TM":{"country":"Turkmenistan","id":"TM","projects":11,"budget":2676.67,"flag":"/images/flags/tm.png"},"UZ":{"country":"Uzbekistan","id":"UZ","projects":13,"budget":2676.67,"flag":"/images/flags/uz.png"},"AF":{"country":"Afghanistan","id":"AF","projects":25,"budget":182947028.91,"flag":"/images/flags/af.png"},"MV":{"country":"Maldives","id":"MV","projects":11,"budget":2676.67,"flag":"/images/flags/mv.png"},"XK":{"country":"Kosovo","id":"XK","projects":12,"budget":2676.67,"flag":"/images/flags/xk.png"},"RS":{"country":"Serbia","id":"RS","projects":14,"budget":2676.67,"flag":"/images/flags/rs.png"},"BA":{"country":"Bosnia and Herzegovina","id":"BA","projects":14,"budget":2563559.83,"flag":"/images/flags/ba.png"},"ME":{"country":"Montenegro","id":"ME","projects":12,"budget":2676.67,"flag":"/images/flags/me.png"},"MK":{"country":"North Macedonia","id":"MK","projects":13,"budget":2676.67,"flag":"/images/flags/mk.png"},"UA":{"country":"Ukraine","id":"UA","projects":15,"budget":232668.67,"flag":"/images/flags/ua.png"},"BY":{"country":"Belarus","id":"BY","projects":11,"budget":2676.67,"flag":"/images/flags/by.png"},"MD":{"country":"Moldova (the Republic of)","id":"MD","projects":14,"budget":4503661.95,"flag":"/images/flags/md.png"},"NR":{"country":"Nauru","id":"NR","projects":11,"budget":2676.67,"flag":"/images/flags/nr.png"},"MH":{"country":"Marshall Islands (the)","id":"MH","projects":11,"budget":2676.67,"flag":"/images/flags/mh.png"},"PW":{"country":"Palau","id":"PW","projects":11,"budget":2676.67,"flag":"/images/flags/pw.png"},"NU":{"country":"Niue","id":"NU","projects":11,"budget":2676.67,"flag":"/images/flags/nu.png"},"TK":{"country":"Tokelau","id":"TK","projects":11,"budget":2676.67,"flag":"/images/flags/tk.png"},"WF":{"country":"Wallis and Futuna","id":"WF","projects":11,"budget":2676.67,"flag":"/images/flags/wf.png"},"YT":{"country":"Mayotte","id":"YT","projects":9,"budget":2676.67,"flag":"/images/flags/yt.png"},"BS":{"country":"Bahamas (the)","id":"BS","projects":9,"budget":2676.67,"flag":"/images/flags/bs.png"},"BB":{"country":"Barbados","id":"BB","projects":9,"budget":2676.67,"flag":"/images/flags/bb.png"},"AN":{"country":"Netherlands Antilles","id":"AN","projects":9,"budget":2676.67,"flag":"/images/flags/an.png"},"AW":{"country":"Aruba","id":"AW","projects":9,"budget":2676.67,"flag":"/images/flags/aw.png"},"TT":{"country":"Trinidad and Tobago","id":"TT","projects":9,"budget":2676.67,"flag":"/images/flags/tt.png"},"AI":{"country":"Anguilla","id":"AI","projects":9,"budget":2676.67,"flag":"/images/flags/ai.png"},"KN":{"country":"Saint Kitts and Nevis","id":"KN","projects":9,"budget":2676.67,"flag":"/images/flags/kn.png"},"KY":{"country":"Cayman Islands (the)","id":"KY","projects":9,"budget":2676.67,"flag":"/images/flags/ky.png"},"TC":{"country":"Turks and Caicos Islands (the)","id":"TC","projects":9,"budget":2676.67,"flag":"/images/flags/tc.png"},"VG":{"country":"Virgin Islands (British)","id":"VG","projects":9,"budget":2676.67,"flag":"/images/flags/vg.png"},"FK":{"country":"Falkland Islands (the) [Malvinas]","id":"FK","projects":9,"budget":2676.67,"flag":"/images/flags/fk.png"},"BN":{"country":"Brunei Darussalam","id":"BN","projects":9,"budget":2676.67,"flag":"/images/flags/bn.png"},"TW":{"country":"Taiwan (Province of China)","id":"TW","projects":9,"budget":2676.67,"flag":"/images/flags/tw.png"},"HK":{"country":"Hong Kong","id":"HK","projects":9,"budget":2676.67,"flag":"/images/flags/hk.png"},"KR":{"country":"Korea (the Republic of)","id":"KR","projects":9,"budget":2676.67,"flag":"/images/flags/kr.png"},"MO":{"country":"Macao","id":"MO","projects":9,"budget":2676.67,"flag":"/images/flags/mo.png"},"BH":{"country":"Bahrain","id":"BH","projects":9,"budget":2676.67,"flag":"/images/flags/bh.png"},"IL":{"country":"Israel","id":"IL","projects":9,"budget":2676.67,"flag":"/images/flags/il.png"},"KW":{"country":"Kuwait","id":"KW","projects":9,"budget":2676.67,"flag":"/images/flags/kw.png"},"OM":{"country":"Oman","id":"OM","projects":9,"budget":2676.67,"flag":"/images/flags/om.png"},"QA":{"country":"Qatar","id":"QA","projects":9,"budget":2676.67,"flag":"/images/flags/qa.png"},"SA":{"country":"Saudi Arabia","id":"SA","projects":9,"budget":2676.67,"flag":"/images/flags/sa.png"},"AE":{"country":"United Arab Emirates (the)","id":"AE","projects":9,"budget":2676.67,"flag":"/images/flags/ae.png"},"CY":{"country":"Cyprus","id":"CY","projects":9,"budget":2676.67,"flag":"/images/flags/cy.png"},"GI":{"country":"Gibraltar","id":"GI","projects":9,"budget":2676.67,"flag":"/images/flags/gi.png"},"MT":{"country":"Malta","id":"MT","projects":9,"budget":2676.67,"flag":"/images/flags/mt.png"},"SI":{"country":"Slovenia","id":"SI","projects":9,"budget":2676.67,"flag":"/images/flags/si.png"},"HR":{"country":"Croatia","id":"HR","projects":9,"budget":2676.67,"flag":"/images/flags/hr.png"},"NC":{"country":"New Caledonia","id":"NC","projects":9,"budget":2676.67,"flag":"/images/flags/nc.png"},"MP":{"country":"Northern Mariana Islands (the)","id":"MP","projects":9,"budget":2676.67,"flag":"/images/flags/mp.png"},"PF":{"country":"French Polynesia","id":"PF","projects":9,"budget":2676.67,"flag":"/images/flags/pf.png"},"SC":{"country":"Seychelles","id":"SC","projects":0,"budget":0.0,"flag":"/images/flags/sc.png"},"UY":{"country":"Uruguay","id":"UY","projects":1,"budget":0.0,"flag":"/images/flags/uy.png"},"GB":{"country":"United Kingdom of Great Britain and Northern Ireland (the)","id":"GB","projects":5,"budget":1711774.0,"flag":"/images/flags/gb.png"},"GR":{"country":"Greece","id":"GR","projects":0,"budget":0.0,"flag":"/images/flags/gr.png"},"JP":{"country":"Japan","id":"JP","projects":0,"budget":0.0,"flag":"/images/flags/jp.png"},"RU":{"country":"Russian Federation (the)","id":"RU","projects":0,"budget":0.0,"flag":"/images/flags/ru.png"},"AS":{"country":"American Samoa","id":"AS","projects":0,"budget":0.0,"flag":"/images/flags/as.png"}}]}}
