{
    "FCDO":
    [
        {
            "name":"Foreign, Commonwealth and Development Office",
            "year":"2019",
            "value": 11786,
            "percentage": 77.6,
            "shortName": "FCDO",
            "note": "This figure is calculated by summing the those for the recently combined Department for International Development (DFID) and Foreign and Commonwealth Office (FCO) to reflect the new department. The source data describes these institutions separately."
        }
    ],
    "BEIS":
    [
        {
            "name":"Department for Business, Energy and Industrial Strategy",
            "year":"2019",
            "value": 960,
            "percentage": 6.3,
            "shortName": "BEIS",
            "note": ""
        }
    ],
    "CSSF":
    [
        {
            "name":"Conflict, Stability and Security Fund",
            "year":"2019",
            "value": 659,
            "percentage": 4.3,
            "shortName": "CSSF",
            "note": ""
        }
    ],
    "HO":
    [
        {
            "name":"Home Office",
            "year":"2019",
            "value": 452,
            "percentage": 3.0,
            "shortName": "Home Office",
            "note": ""
        }
    ],
    "DH":
    [
        {
            "name":"Department of Health and Social Care",
            "year":"2019",
            "value": 222,
            "percentage": 1.5,
            "shortName": "DoH",
            "note": ""
        }
    ],
    "PF":
    [
        {
            "name":"Cross-Government Prosperity Fund",
            "year":"2019",
            "value": 176,
            "percentage": 1.2,
            "shortName": "CGPF",
            "note": ""
        }
    ],
    "DEFRA":
    [
        {
            "name":"Department for Environment Food and Rural Affairs",
            "year":"2019",
            "value": 87,
            "percentage": 0.6,
            "shortName": "DEFRA",
            "note": ""
        }
    ],
    "HMT":
    [
        {
            "name":"HM Treasury",
            "year":"2019",
            "value": 80,
            "percentage": 0.5,
            "shortName": "HMT",
            "note": ""
        }
    ],
    "DWP":
    [
        {
            "name":"Department for Work and Pensions",
            "year":"2019",
            "value": 27,
            "percentage": 0.2,
            "shortName": "DWP",
            "note": ""
        }
    ],
    "DFE":
    [
        {
            "name":"Department for Education",
            "year":"2019",
            "value": 21,
            "percentage": 0.1,
            "shortName": "DoE",
            "note": ""
        }
    ],
    "HMRC":
    [
        {
            "name":"HM Revenue and Customs",
            "year":"2019",
            "value": 13,
            "percentage": 0.1,
            "shortName": "HMRC",
            "note": ""
        }
    ],
    "DCMS":
    [
        {
            "name":"Department for Culture, Media and Sports",
            "year":"2019",
            "value": 12,
            "percentage": 0.1,
            "shortName": "DCMS",
            "note": ""
        }
    ],
    "MOD":
    [
        {
            "name":"Ministry of Defence",
            "year":"2019",
            "value": 6,
            "percentage": 0.0,
            "shortName": "MOD",
            "note": ""
        }
    ],
    "DIT":
    [
        {
            "name":"Department of International Trade",
            "year":"2019",
            "value": 2,
            "percentage": 0.0,
            "shortName": "DIT",
            "note": ""
        }
    ]
}